pyfluids/__init__.py
pyfluids/config/__init__.py
pyfluids/config/pyfluids_config.py
pyfluids/config/pyfluids_config_builder.py
pyfluids/config/singleton.py
pyfluids/config/unit_converter.py
pyfluids/config/units_system.py
pyfluids/enums/__init__.py
pyfluids/enums/fluids_list.py
pyfluids/enums/mix.py
pyfluids/enums/phases.py
pyfluids/fluids/__init__.py
pyfluids/fluids/abstract_fluid.py
pyfluids/fluids/fluid.py
pyfluids/fluids/mixture.py
pyfluids/humid_air/__init__.py
pyfluids/humid_air/humid_air.py
pyfluids/io/__init__.py
pyfluids/io/abstract_input.py
pyfluids/io/input.py
pyfluids/io/input_humid_air.py
pyfluids/io/outputs_validator.py
pyfluids-2.8.2.dist-info/METADATA
pyfluids-2.8.2.dist-info/WHEEL
pyfluids-2.8.2.dist-info/licenses/LICENSE
pyfluids-2.8.2.dist-info/RECORD
