Metadata-Version: 2.4
Name: pyfluids
Version: 2.8.2
Summary: Simple, full-featured, lightweight CoolProp wrapper for Python
License: MIT
License-File: LICENSE
Keywords: CoolProp,fluids,mixtures,humid,air,thermophysical,properties,thermodynamics
Author: Vladimir Portyanikhin
Author-email: v.portyanikhin@ya.ru
Requires-Python: >=3.9,<3.14
Classifier: Development Status :: 5 - Production/Stable
Classifier: Intended Audience :: Developers
Classifier: Intended Audience :: Education
Classifier: Intended Audience :: Manufacturing
Classifier: Intended Audience :: Science/Research
Classifier: License :: OSI Approved :: MIT License
Classifier: Natural Language :: English
Classifier: Operating System :: MacOS
Classifier: Operating System :: Microsoft :: Windows
Classifier: Operating System :: POSIX :: Linux
Classifier: Operating System :: Unix
Classifier: Programming Language :: Python
Classifier: Programming Language :: Python :: 3
Classifier: Programming Language :: Python :: 3.9
Classifier: Programming Language :: Python :: 3.10
Classifier: Programming Language :: Python :: 3.11
Classifier: Programming Language :: Python :: 3.12
Classifier: Programming Language :: Python :: 3.13
Classifier: Programming Language :: Python :: 3 :: Only
Classifier: Programming Language :: Python :: Implementation
Classifier: Programming Language :: Python :: Implementation :: PyPy
Classifier: Topic :: Education
Classifier: Topic :: Scientific/Engineering
Classifier: Topic :: Scientific/Engineering :: Atmospheric Science
Classifier: Topic :: Scientific/Engineering :: Chemistry
Classifier: Topic :: Scientific/Engineering :: Physics
Requires-Dist: CoolProp (==7.1.0)
Requires-Dist: tomli (==2.2.1)
Project-URL: Documentation, https://github.com/portyanikhin/PyFluids
Project-URL: Homepage, https://github.com/portyanikhin/PyFluids
Project-URL: Repository, https://github.com/portyanikhin/PyFluids
